MANIFEST.in
README.rst
setup.cfg
setup.py
tw2/__init__.py
tw2.jqplugins.fg.egg-info/PKG-INFO
tw2.jqplugins.fg.egg-info/SOURCES.txt
tw2.jqplugins.fg.egg-info/dependency_links.txt
tw2.jqplugins.fg.egg-info/entry_points.txt
tw2.jqplugins.fg.egg-info/namespace_packages.txt
tw2.jqplugins.fg.egg-info/not-zip-safe
tw2.jqplugins.fg.egg-info/requires.txt
tw2.jqplugins.fg.egg-info/top_level.txt
tw2/jqplugins/__init__.py
tw2/jqplugins/fg/__init__.py
tw2/jqplugins/fg/base.py
tw2/jqplugins/fg/defaults.py
tw2/jqplugins/fg/samples.py
tw2/jqplugins/fg/widgets.py
tw2/jqplugins/fg/static/jquery/fg/css/fg.menu.css
tw2/jqplugins/fg/static/jquery/fg/js/fg.menu.js
tw2/jqplugins/fg/templates/__init__.py
tw2/jqplugins/fg/templates/__init__.pyc
tw2/jqplugins/fg/templates/menu.html
tw2/jqplugins/fg/templates/menu.mak
tw2/jqplugins/fg/templates/recursive_menu.html
tw2/jqplugins/fg/templates/recursive_menu.mak