Metadata-Version: 1.0
Name: tw2.jqplugins.fg
Version: 2.0b9
Summary: toscawidgets2 wrapper for random filament group tools
Home-page: http://github.com/ralphbean/tw2.jqplugins.fg
Author: Ralph Bean
Author-email: ralph.bean@gmail.com
License: MIT
Keywords: toscawidgets.widgets
Platform: UNKNOWN
Classifier: Development Status :: 3 - Alpha
Classifier: Environment :: Web Environment
Classifier: Environment :: Web Environment :: ToscaWidgets
Classifier: Topic :: Software Development :: Libraries :: Python Modules
Classifier: Topic :: Software Development :: Widget Sets
Classifier: Intended Audience :: Developers
Classifier: Operating System :: OS Independent
Classifier: Programming Language :: Python
